{
  "packageName": "com.mobstac.thehindu",
  "environment": "development",
  "resolution": "xxhdpi",
  "configJson": {
    "lastServerUpdateTime": "UTC-TIME",
    "vokkleId": "432081eb-6e8e-4abc-a88f-ca5357aa7244",
    "refreshIntervalInMins": "5",
    "importantMsg": {
      "title": "Title",
      "msg": "This msg on update of config (not required always, if exist will be shown to user only once)"
    },
    "staticItem": [
      {
        "title": "Terms & Condition",
        "urlDark": "https://alphabl.businessline.in/app/termsofusedark/",
        "urlLight": "https://alphabl.businessline.in/app/termsofuselite/"
      },
      {
        "title": "Privacy Policy",
        "urlDark": "https://alphabl.businessline.in/app/Privacypolicydark/",
        "urlLight": "https://alphabl.businessline.in/app/Privacypolicylite/"
      },
      {
        "title": "Help",
        "urlDark": "https://alphabl.businessline.in/app/helpdark/",
        "urlLight": "https://alphabl.businessline.in/app/helplite/"
      },
      {
        "title": "AboutUs",
        "urlDark": "https://alphabl.businessline.in/app/aboutusdark/",
        "urlLight": "https://alphabl.businessline.in/app/aboutuslite/"
      }
    ],
    "tabs": [
      {
        "title": "Home",
        "iconUrl": {
          "urlDark": "https://appsearch.thehindu.com/admin/assets/icons/th/Light/xxhdpi/unfavorite.png",
          "urlSelectedDark": "https://appsearch.thehindu.com/admin/assets/icons/th/Dark/xxhdpi/favorite.png",
          "urlLight": "https://appsearch.thehindu.com/admin/assets/icons/th/Light/xxhdpi/unfavorite.png",
          "urlSelectedLight": "https://appsearch.thehindu.com/admin/assets/icons/th/Light/xxhdpi/favorite.png"
        },
        "group": "GROUP_DEFAULT_SECTIONS",
        "pageSource": "GROUP_DEFAULT_SECTIONS"
      },
      {
        "title": "Briefing",
        "iconUrl": {
          "urlDark": "https://appsearch.thehindu.com/admin/assets/icons/th/Light/xxhdpi/unfavorite.png",
          "urlSelectedDark": "https://appsearch.thehindu.com/admin/assets/icons/th/Dark/xxhdpi/favorite.png",
          "urlLight": "https://appsearch.thehindu.com/admin/assets/icons/th/Light/xxhdpi/unfavorite.png",
          "urlSelectedLight": "https://appsearch.thehindu.com/admin/assets/icons/th/Light/xxhdpi/favorite.png"
        },
        "group": "GROUP_PREMIUM_SECTIONS",
        "pageSource": "Briefing"
      },
      {
        "title": "My Stories",
        "iconUrl": {
          "urlDark": "https://appsearch.thehindu.com/admin/assets/icons/th/Light/xxhdpi/unfavorite.png",
          "urlSelectedDark": "https://appsearch.thehindu.com/admin/assets/icons/th/Dark/xxhdpi/favorite.png",
          "urlLight": "https://appsearch.thehindu.com/admin/assets/icons/th/Light/xxhdpi/unfavorite.png",
          "urlSelectedLight": "https://appsearch.thehindu.com/admin/assets/icons/th/Dark/xxhdpi/favorite.png"
        },
        "group": "GROUP_PREMIUM_SECTIONS",
        "pageSource": "My Stories"
      },
      {
        "title": "Suggested",
        "iconUrl": {
          "urlDark": "https://appsearch.thehindu.com/admin/assets/icons/th/Light/xxhdpi/unfavorite.png",
          "urlSelectedDark": "https://appsearch.thehindu.com/admin/assets/icons/th/Dark/xxhdpi/favorite.png",
          "urlLight": "https://appsearch.thehindu.com/admin/assets/icons/th/Light/xxhdpi/unfavorite.png",
          "urlSelectedLight": "https://appsearch.thehindu.com/admin/assets/icons/th/Dark/xxhdpi/favorite.png"
        },
        "group": "GROUP_PREMIUM_SECTIONS",
        "pageSource": "Suggested"
      },
      {
        "title": "Profile",
        "iconUrl": {
          "urlDark": "https://appsearch.thehindu.com/admin/assets/icons/th/Light/xxhdpi/unfavorite.png",
          "urlSelectedDark": "https://appsearch.thehindu.com/admin/assets/icons/th/Dark/xxhdpi/favorite.png",
          "urlLight": "https://appsearch.thehindu.com/admin/assets/icons/th/Light/xxhdpi/unfavorite.png",
          "urlSelectedLight": "https://appsearch.thehindu.com/admin/assets/icons/th/Dark/xxhdpi/favorite.png"
        },
        "group": "GROUP_PREMIUM_SECTIONS",
        "pageSource": "Profile"
      }
    ],
    "appTheme": {
      "textColors": {
        "dark": {
          "XL": "#000000",
          "L": "#000000",
          "M": "#000000",
          "S": "#818181",
          "XS": "#818181",
          "detailpageText": "#000000"
        },
        "light": {
          "XL": "#ffffff",
          "L": "#ffffff",
          "M": "#ffffff",
          "S": "#818181",
          "XS": "#818181",
          "detailpageText": "#ffffff"
        }
      },
      "tilesBg": {
        "dark": "#191919",
        "light": "#ffffff"
      },
      "screenBg": {
        "dark": "#191919",
        "light": "#ffffff"
      },
      "topBarBg": {
        "dark": "#000000",
        "light": "#ffffff"
      },
      "bottomBar": {
        "text": {
          "dark": "#818181",
          "darkSelected": "#ededed",
          "light": "#818181",
          "lightSelected": "#424242"
        },
        "bg": {
          "dark": "#000000",
          "light": "#ffffff"
        },
        "indicator": {
          "dark": "#00000000",
          "light": "#00000000"
        }
      },
      "breadcrumb": {
        "text": {
          "dark": "#818181",
          "darkSelected": "#ffffff",
          "light": "#818181",
          "lightSelected": "#000000"
        },
        "bg": {
          "dark": "#191919",
          "light": "#ffffff"
        },
        "indicator": {
          "dark": "#1b528e",
          "light": "#191919"
        }
      },
      "systemTopBarBackground": {
        "light": "#e0e0e0",
        "dark": "#4a4a4a"
      },
      "systemBottomBarBackground": {
        "light": "#e0e0e0",
        "dark": "#000000"
      }
    },
    "widget": [
      {
        "secId": "142",
        "index": "5",
        "itemCount": "7",
        "background": {
          "dark": "#191919",
          "light": "#ffffff"
        },
        "description": {
          "dark": "#ffffff",
          "light": "#191919"
        },
        "title": {
          "dark": "#E7E73C",
          "light": "#E73CE5"
        },
        "viewAll": {
          "dark": "#E7603C",
          "light": "#3C70E7"
        }
      },
      {
        "secId": "88",
        "index": "8",
        "itemCount": "7",
        "background": {
          "dark": "#191919",
          "light": "#ffffff"
        },
        "description": {
          "dark": "#ffffff",
          "light": "#191919"
        },
        "title": {
          "dark": "#E7E73C",
          "light": "#E73CE5"
        },
        "viewAll": {
          "dark": "#E7603C",
          "light": "#3C70E7"
        }
      },
      {
        "secId": "5",
        "index": "10",
        "itemCount": "7",
        "background": {
          "dark": "#191919",
          "light": "#ffffff"
        },
        "description": {
          "dark": "#ffffff",
          "light": "#191919"
        },
        "title": {
          "dark": "#E7E73C",
          "light": "#E73CE5"
        },
        "viewAll": {
          "dark": "#E7603C",
          "light": "#3C70E7"
        }
      },
      {
        "secId": "138",
        "index": "12",
        "itemCount": "7",
        "background": {
          "dark": "#191919",
          "light": "#ffffff"
        },
        "description": {
          "dark": "#ffffff",
          "light": "#191919"
        },
        "title": {
          "dark": "#E7E73C",
          "light": "#E73CE5"
        },
        "viewAll": {
          "dark": "#E7603C",
          "light": "#3C70E7"
        }
      },
      {
        "secId": "69",
        "index": "15",
        "itemCount": "7",
        "background": {
          "dark": "#191919",
          "light": "#ffffff"
        },
        "description": {
          "dark": "#ffffff",
          "light": "#191919"
        },
        "title": {
          "dark": "#E7E73C",
          "light": "#E73CE5"
        },
        "viewAll": {
          "dark": "#E7603C",
          "light": "#3C70E7"
        }
      }
    ],
    "Ads": {
      "bottomAdHomeId": "/22390678/Hindu_Android_HP_Sticky",
      "bottomAdOtherId": "/22390678/Hindu_Android_AT_Sticky",
      "fullScreenAdId": "/22390678/Hindu_Android_Interstitial",
      "detailPageTopAdId": "/22390678/Hindu_Android_AT_Middle",
      "detailPageBottomAdId": "/22390678/Hindu_Android_AT_Bottom",
      "listingPageAds": [
        {
          "type": "DFP",
          "adId": "/22390678/Hindu_Android_HP_Middle",
          "index": "4"
        },
        {
          "type": "taboola",
          "index": "6"
        },
        {
          "type": "DFP",
          "adId": "/22390678/Hindu_Android_HP_Footer",
          "index": "8"
        },
        {
          "type": "taboola",
          "index": "10"
        },
        {
          "type": "DFP",
          "adId": "/22390678/Hindu_Android_HP_Bottom",
          "index": "12"
        },
        {
          "type": "taboola",
          "index": "13"
        },
        {
          "type": "DFP",
          "adId": "/22390678/Hindu_Android_HP_Middle",
          "index": "16"
        },
        {
          "type": "taboola",
          "index": "18"
        },
        {
          "type": "DFP",
          "adId": "/22390678/Hindu_Android_HP_Middle",
          "index": "20"
        }
      ]
    },
    "taboola": {
      "id": "thehindu-hinduappandroid",
      "apikey": "65e50cbad5e7e156f110d188630a733c8054f54b",
      "publisher": "thehindu-hinduappandroid",
      "pageType": "article",
      "mode": "thumbnails-a",
      "placementLight": "Below Article Thumbnails",
      "placementDark": "Below Article Thumbnails Dark",
      "taboolaNativeAd": {
        "placement_home": "Below Home Stream",
        "placement_home_source_type": "home",
        "placement_section": "Below Section Stream",
        "placement_section_source_type": "section",
        "placement_detail": "Below Article Stream"
      }
    },
    "totalIcons": "88",
    "otherIconsDownloadUrls": {
      "dark": {
        "Logo": "https://appsearch.thehindu.com/admin/assets/icons/th/Dark/xxhdpi/Logo.png",
        "Listing": {
          "bookmark": "https://appsearch.thehindu.com/admin/assets/icons/th/Dark/xxhdpi/bookmark.png",
          "unbookmark": "https://appsearch.thehindu.com/admin/assets/icons/th/Dark/xxhdpi/unbookmark.png",
          "like": "https://appsearch.thehindu.com/admin/assets/icons/th/Dark/xxhdpi/like.png",
          "dislike": "https://appsearch.thehindu.com/admin/assets/icons/th/Dark/xxhdpi/dislike.png",
          "favorite": "https://appsearch.thehindu.com/admin/assets/icons/th/Dark/xxhdpi/favorite.png",
          "unfavorite": "https://appsearch.thehindu.com/admin/assets/icons/th/Dark/xxhdpi/unfavorite.png",
          "share": "https://appsearch.thehindu.com/admin/assets/icons/th/Dark/xxhdpi/share.png"
        },
        "topbar": {
          "left_slider_three_line": "https://appsearch.thehindu.com/admin/assets/icons/th/Dark/xxhdpi/left_slider_three_line.png",
          "logo": "https://appsearch.thehindu.com/admin/assets/icons/th/Dark/xxhdpi/logo_actionbar.png",
          "search": "https://appsearch.thehindu.com/admin/assets/icons/th/Dark/xxhdpi/search.png",
          "overflow_verticle_dot": "https://appsearch.thehindu.com/admin/assets/icons/th/Dark/xxhdpi/overflow_verticle_dot.png",
          "back": "https://appsearch.thehindu.com/admin/assets/icons/th/Dark/xxhdpi/back.png",
          "ttsPlay": "https://appsearch.thehindu.com/admin/assets/icons/th/Dark/xxhdpi/ttsPlay.png",
          "ttsPause": "https://appsearch.thehindu.com/admin/assets/icons/th/Dark/xxhdpi/ttsPause.png",
          "comment": "https://appsearch.thehindu.com/admin/assets/icons/th/Dark/xxhdpi/comment.png",
          "bookmark": "https://appsearch.thehindu.com/admin/assets/icons/th/Dark/xxhdpi/bookmark.png",
          "unbookmark": "https://appsearch.thehindu.com/admin/assets/icons/th/Dark/xxhdpi/unbookmark.png",
          "textSize": "https://appsearch.thehindu.com/admin/assets/icons/th/Dark/xxhdpi/textSize.png",
          "share": "https://appsearch.thehindu.com/admin/assets/icons/th/Dark/xxhdpi/share.png",
          "crown": "https://appsearch.thehindu.com/admin/assets/icons/th/Dark/xxhdpi/crown.png",
          "like": "https://appsearch.thehindu.com/admin/assets/icons/th/Dark/xxhdpi/like.png",
          "dislike": "https://appsearch.thehindu.com/admin/assets/icons/th/Dark/xxhdpi/dislike.png",
          "favorite": "https://appsearch.thehindu.com/admin/assets/icons/th/Dark/xxhdpi/favorite.png",
          "unfavorite": "https://appsearch.thehindu.com/admin/assets/icons/th/Dark/xxhdpi/unfavorite.png",
          "cross": "https://ashwani1387.s3.ap-south-1.amazonaws.com/cross_light.png",
          "refresh": "https://ashwani1387.s3.ap-south-1.amazonaws.com/refresh_dark.png"
        },
        "placeHolder": {
          "banner": "https://appsearch.thehindu.com/admin/assets/icons/th/Dark/xxhdpi/banner-b.png",
          "thumb": "https://appsearch.thehindu.com/admin/assets/icons/th/Dark/xxhdpi/thumb-b.png",
          "widget": "https://appsearch.thehindu.com/admin/assets/icons/th/Dark/xxhdpi/widget-b.png",
          "ads": "https://appsearch.thehindu.com/admin/assets/icons/th/Dark/xxhdpi/ads.png"
        }
      },
      "light": {
        "Logo": "https://appsearch.thehindu.com/admin/assets/icons/th/Light/xxhdpi/Logo.png",
        "Listing": {
          "bookmark": "https://appsearch.thehindu.com/admin/assets/icons/th/Light/xxhdpi/bookmark.png",
          "unbookmark": "https://appsearch.thehindu.com/admin/assets/icons/th/Light/xxhdpi/unbookmark.png",
          "like": "https://appsearch.thehindu.com/admin/assets/icons/th/Light/xxhdpi/like.png",
          "dislike": "https://appsearch.thehindu.com/admin/assets/icons/th/Light/xxhdpi/dislike.png",
          "favorite": "https://appsearch.thehindu.com/admin/assets/icons/th/Light/xxhdpi/favorite.png",
          "unfavorite": "https://appsearch.thehindu.com/admin/assets/icons/th/Light/xxhdpi/unfavorite.png",
          "share": "https://appsearch.thehindu.com/admin/assets/icons/th/Light/xxhdpi/share.png"
        },
        "topbar": {
          "left_slider_three_line": "https://appsearch.thehindu.com/admin/assets/icons/th/Light/xxhdpi/left_slider_three_line.png",
          "logo": "https://appsearch.thehindu.com/admin/assets/icons/th/Light/xxhdpi/logo_actionbar.png",
          "search": "https://appsearch.thehindu.com/admin/assets/icons/th/Light/xxhdpi/search.png",
          "overflow_verticle_dot": "https://appsearch.thehindu.com/admin/assets/icons/th/Light/xxhdpi/overflow_verticle_dot.png",
          "back": "https://appsearch.thehindu.com/admin/assets/icons/th/Light/xxhdpi/back.png",
          "ttsPlay": "https://appsearch.thehindu.com/admin/assets/icons/th/Light/xxhdpi/ttsPlay.png",
          "ttsPause": "https://appsearch.thehindu.com/admin/assets/icons/th/Light/xxhdpi/ttsPause.png",
          "comment": "https://appsearch.thehindu.com/admin/assets/icons/th/Light/xxhdpi/comment.png",
          "bookmark": "https://appsearch.thehindu.com/admin/assets/icons/th/Light/xxhdpi/bookmark.png",
          "unbookmark": "https://appsearch.thehindu.com/admin/assets/icons/th/Light/xxhdpi/unbookmark.png",
          "textSize": "https://appsearch.thehindu.com/admin/assets/icons/th/Light/xxhdpi/textSize.png",
          "share": "https://appsearch.thehindu.com/admin/assets/icons/th/Light/xxhdpi/share.png",
          "crown": "https://appsearch.thehindu.com/admin/assets/icons/th/Light/xxhdpi/crown.png",
          "like": "https://appsearch.thehindu.com/admin/assets/icons/th/Light/xxhdpi/like.png",
          "dislike": "https://appsearch.thehindu.com/admin/assets/icons/th/Light/xxhdpi/dislike.png",
          "favorite": "https://appsearch.thehindu.com/admin/assets/icons/th/Light/xxhdpi/favorite.png",
          "unfavorite": "https://appsearch.thehindu.com/admin/assets/icons/th/Light/xxhdpi/unfavorite.png",
          "cross": "https://ashwani1387.s3.ap-south-1.amazonaws.com/cross_light.png",
          "refresh": "https://ashwani1387.s3.ap-south-1.amazonaws.com/refresh_light.png"
        },
        "placeHolder": {
          "banner": "https://appsearch.thehindu.com/admin/assets/icons/th/Light/xxhdpi/banner-b.png",
          "thumb": "https://appsearch.thehindu.com/admin/assets/icons/th/Light/xxhdpi/thumb-b.png",
          "widget": "https://appsearch.thehindu.com/admin/assets/icons/th/Light/xxhdpi/widget-b.png",
          "ads": "https://appsearch.thehindu.com/admin/assets/icons/th/Light/xxhdpi/ads.png"
        }
      }
    },
    "subSectionsIndex": "3",
    "contentUrl": {
      "baseUrlDefault": "https://app.thehindu.com/hindu/service/api_v1.004/",
      "newsDigest": "https://appsearch.thehindu.com/hindu/service/api_v3/mobiles/newsLetter.php"
    },
    "searchOption": {
      "urlId": "https://thehindu.com/app/getArticleByIds.json?articleIds=",
      "urlText": "https://www.thehindu.com/app/search.json?term=",
      "searchItem": [
        {
          "title": "Article",
          "searchType": "article"
        }
      ]
    }
  }
}